{"cameraMode":{"drawMode":0,"name":"Shaded","section":"Shading Mode"},"sceneLighting":true,"audioPlay":false,"sceneViewState":{"m_AlwaysRefresh":false,"showFog":true,"showSkybox":true,"showFlares":true,"showImageEffects":true,"showParticleSystems":true,"showVisualEffectGraphs":true,"m_FxEnabled":true},"in2DMode":false,"pivot":{"x":8.518782615661621,"y":1.531665325164795,"z":4.1131744384765629},"rotation":{"x":-0.016781292855739595,"y":0.057558540254831317,"z":-0.0009644274832680821,"w":-0.9982216358184815},"size":3.632963180541992,"orthographic":false}